odoo/addons/pos_order_to_sale_order/README.rst
odoo/addons/pos_order_to_sale_order/__init__.py
odoo/addons/pos_order_to_sale_order/__manifest__.py
odoo/addons/pos_order_to_sale_order/i18n/ca.po
odoo/addons/pos_order_to_sale_order/i18n/es.po
odoo/addons/pos_order_to_sale_order/i18n/fr.po
odoo/addons/pos_order_to_sale_order/i18n/it.po
odoo/addons/pos_order_to_sale_order/i18n/pos_order_to_sale_order.pot
odoo/addons/pos_order_to_sale_order/i18n/pt_BR.po
odoo/addons/pos_order_to_sale_order/models/__init__.py
odoo/addons/pos_order_to_sale_order/models/pos_config.py
odoo/addons/pos_order_to_sale_order/models/res_config_settings.py
odoo/addons/pos_order_to_sale_order/models/sale_order.py
odoo/addons/pos_order_to_sale_order/models/sale_order_line.py
odoo/addons/pos_order_to_sale_order/readme/CONFIGURE.md
odoo/addons/pos_order_to_sale_order/readme/CONTRIBUTORS.md
odoo/addons/pos_order_to_sale_order/readme/DESCRIPTION.md
odoo/addons/pos_order_to_sale_order/readme/DEVELOP.md
odoo/addons/pos_order_to_sale_order/readme/USAGE.md
odoo/addons/pos_order_to_sale_order/static/description/icon.png
odoo/addons/pos_order_to_sale_order/static/description/index.html
odoo/addons/pos_order_to_sale_order/static/description/pos_frontend_button.png
odoo/addons/pos_order_to_sale_order/static/description/pos_frontend_popup.png
odoo/addons/pos_order_to_sale_order/static/description/res_config_settings_form.png
odoo/addons/pos_order_to_sale_order/static/src/css/pos.scss
odoo/addons/pos_order_to_sale_order/static/src/js/CreateOrderButton.esm.js
odoo/addons/pos_order_to_sale_order/static/src/js/CreateOrderPopup.esm.js
odoo/addons/pos_order_to_sale_order/static/src/xml/CreateOrderButton.xml
odoo/addons/pos_order_to_sale_order/static/src/xml/CreateOrderPopup.xml
odoo/addons/pos_order_to_sale_order/static/tests/tours/PosOrderToSaleOrderTour.tour.esm.js
odoo/addons/pos_order_to_sale_order/static/tests/tours/helpers/PosOrderToSaleOrderMethods.esm.js
odoo/addons/pos_order_to_sale_order/tests/__init__.py
odoo_addon_pos_order_to_sale_order-17.0.1.0.1.dist-info/METADATA
odoo_addon_pos_order_to_sale_order-17.0.1.0.1.dist-info/WHEEL
odoo_addon_pos_order_to_sale_order-17.0.1.0.1.dist-info/top_level.txt
odoo_addon_pos_order_to_sale_order-17.0.1.0.1.dist-info/RECORD
